FinalFlow/FinalFlow.py
FinalFlow/FinalFlowConv.py
FinalFlow/__init__.py
OmMariamFlow/Activations.py
OmMariamFlow/Data.py
OmMariamFlow/Function.py
OmMariamFlow/Layers.py
OmMariamFlow/Losses.py
OmMariamFlow/Model.py
OmMariamFlow/OmMariamFlow.py
OmMariamFlow/Optimizations.py
OmMariamFlow/Test_Q8_Sheet4.py
OmMariamFlow/Utils.py
OmMariamFlow/Visualizer.py
OmMariamFlow/__init__.py
FinalFlow-0.0.3.dist-info/LICENSE.txt
FinalFlow-0.0.3.dist-info/METADATA
FinalFlow-0.0.3.dist-info/WHEEL
FinalFlow-0.0.3.dist-info/top_level.txt
FinalFlow-0.0.3.dist-info/RECORD
