Metadata-Version: 2.1
Name: FinalFlow
Version: 0.0.3
Summary: nn framework
Home-page: UNKNOWN
Author: thomas joseph
Author-email: thomasartin@gmail.com
License: MIT
Keywords: nnframework
Platform: UNKNOWN
Classifier: Development Status :: 5 - Production/Stable
Classifier: Intended Audience :: Education
Classifier: Operating System :: OS Independent
Classifier: License :: OSI Approved :: MIT License
Classifier: Programming Language :: Python :: 3
